chase/__init__.py
chase/chase.py
chase/mark_for_capture.xml
chase/orbital_tests.py
chase/order_new.xml
chase/profile_create.xml
chase/profile_destroy.xml
chase/profile_read.xml
chase/profile_update.xml
chase/reversal.xml
chase/test.py
chase-2.1.3.dist-info/LICENSE.txt
chase-2.1.3.dist-info/METADATA
chase-2.1.3.dist-info/WHEEL
chase-2.1.3.dist-info/top_level.txt
chase-2.1.3.dist-info/RECORD
